synconf/__init__.py
synconf/config.py
synconf/exceptions.py
synconf/interpolation.py
synconf/parameter_tracer.py
synconf/parser.py
synconf/utils.py
synconf/validation.py
synconf-0.2.1.dist-info/METADATA
synconf-0.2.1.dist-info/WHEEL
synconf-0.2.1.dist-info/licenses/LICENSE
synconf-0.2.1.dist-info/RECORD
