Metadata-Version: 2.4
Name: synconf
Version: 0.2.1
Summary: Add your description here
Project-URL: Homepage, https://github.com/richarddwang/synconf
Author-email: richarddwang <richardyy1188@gmail.com>
License-File: LICENSE
Requires-Python: >=3.12
Requires-Dist: docstring-parser>=0.17.0
Requires-Dist: python-dotenv>=1.1.1
Requires-Dist: pyyaml>=6.0.2
